AUTHORS.rst
CONTRIBUTING.rst
HISTORY.rst
LICENSE
MANIFEST.in
README.rst
setup.cfg
setup.py
cryptocurrency_payment/__init__.py
cryptocurrency_payment/admin.py
cryptocurrency_payment/app_settings.py
cryptocurrency_payment/apps.py
cryptocurrency_payment/models.py
cryptocurrency_payment/tasks.py
cryptocurrency_payment/urls.py
cryptocurrency_payment/views.py
cryptocurrency_payment/migrations/0001_initial.py
cryptocurrency_payment/migrations/__init__.py
cryptocurrency_payment/static/css/cryptocurrency_payment.css
cryptocurrency_payment/static/js/cryptocurrency_payment.js
cryptocurrency_payment/templates/cryptocurrency_payment/base.html
cryptocurrency_payment/templates/cryptocurrency_payment/payment_detail.html
cryptocurrency_payment/test_utils/__init__.py
cryptocurrency_payment/test_utils/test_app/__init__.py
cryptocurrency_payment/test_utils/test_app/admin.py
cryptocurrency_payment/test_utils/test_app/apps.py
cryptocurrency_payment/test_utils/test_app/models.py
cryptocurrency_payment/test_utils/test_app/migrations/0001_initial.py
cryptocurrency_payment/test_utils/test_app/migrations/__init__.py
django_cryptocurrency_payment.egg-info/PKG-INFO
django_cryptocurrency_payment.egg-info/SOURCES.txt
django_cryptocurrency_payment.egg-info/dependency_links.txt
django_cryptocurrency_payment.egg-info/not-zip-safe
django_cryptocurrency_payment.egg-info/requires.txt
django_cryptocurrency_payment.egg-info/top_level.txt