Metadata-Version: 1.1
Name: django-cryptocurrency-payment
Version: 0.1.1
Summary: Simple and flexible pluggable cryptocurrency payment app for django
Home-page: https://github.com/ydaniels/django-cryptocurrency-payment
Author: Yomi Daniel
Author-email: yomid4all@gamil.com
License: MIT
Keywords: django-cryptocurrency-payment
Platform: UNKNOWN
Classifier: Development Status :: 3 - Alpha
Classifier: Framework :: Django :: 2.1
Classifier: Intended Audience :: Developers
Classifier: License :: OSI Approved :: BSD License
Classifier: Natural Language :: English
Classifier: Programming Language :: Python :: 2
Classifier: Programming Language :: Python :: 2.7
Classifier: Programming Language :: Python :: 3
Classifier: Programming Language :: Python :: 3.5
Classifier: Programming Language :: Python :: 3.6
Classifier: Programming Language :: Python :: 3.7
Classifier: Programming Language :: Python :: 3.8
